README.md
setup.py
src/data/__init__.py
src/data/data.py
src/model/__init__.py
src/model/attention.py
src/model/base_model.py
src/model/lm.py
src/multi_emotion_recognition.egg-info/PKG-INFO
src/multi_emotion_recognition.egg-info/SOURCES.txt
src/multi_emotion_recognition.egg-info/dependency_links.txt
src/multi_emotion_recognition.egg-info/requires.txt
src/multi_emotion_recognition.egg-info/top_level.txt
src/utils/__init__.py
src/utils/callbacks.py
src/utils/conf.py
src/utils/data.py
src/utils/logging.py
src/utils/losses.py
src/utils/metrics.py
src/utils/optim.py
src/utils/utils.py