Metadata-Version: 2.1
Name: multi-emotion-recognition
Version: 0.1.2
Summary: detect multiple emotions in a sentence including [anger, anticipation, disgust, fear, joy, love, optimism, pessimism, sadness,                    surprise, trust]
Home-page: https://github.com/JinfenLi/multi_emotion_recognition
Author: Jinfen Li
Author-email: jli284@syr.edu
License: MIT
Classifier: Programming Language :: Python :: 3
Classifier: License :: OSI Approved :: Apache Software License
